spfwhitelister/__init__.py
spfwhitelister/__main__.py
spfwhitelister-0.0.1.dist-info/LICENSE.txt
spfwhitelister-0.0.1.dist-info/METADATA
spfwhitelister-0.0.1.dist-info/WHEEL
spfwhitelister-0.0.1.dist-info/entry_points.txt
spfwhitelister-0.0.1.dist-info/top_level.txt
spfwhitelister-0.0.1.dist-info/RECORD
