Metadata-Version: 2.1
Name: spfwhitelister
Version: 0.0.1
Summary: Library/utility to maintain a list of while listed domains.
Home-page: http://github.com/frawau/spfwhitelister
Author: François Wautier
Author-email: francois@wautier.eu
License: MIT
Keywords: greylist,MTA
Platform: UNKNOWN
Classifier: License :: OSI Approved :: MIT License
Classifier: Programming Language :: Python :: 3
Requires-Dist: dnspython
